pravaha/__init__.py
pravaha/cli/__init__.py
pravaha/cli/main.py
pravaha/cli/parser.py
pravaha/cli/runner.py
pravaha/context/__init__.py
pravaha/context/condition/__init__.py
pravaha/context/condition/builders.py
pravaha/context/condition/context.py
pravaha/core/__init__.py
pravaha/core/executor.py
pravaha/core/registry.py
pravaha/core/task.py
pravaha/enums/__init__.py
pravaha/enums/task_priority.py
pravaha/enums/task_status.py
pravaha/exception/__init__.py
pravaha/exception/tag.py
pravaha/exception/task.py
pravaha/exception/validation.py
pravaha/report/__init__.py
pravaha/report/report.py
pravaha/retry/__init__.py
pravaha/retry/backoff.py
pravaha/retry/policy.py
pravaha/utils/__init__.py
pravaha/utils/dep_resolver.py
pravaha/utils/execution_plan.py
pravaha/utils/logger.py
pravaha/utils/utilities.py
pravaha/validation/__init__.py
pravaha/validation/dag.py
pravaha-1.0.0.dist-info/METADATA
pravaha-1.0.0.dist-info/WHEEL
pravaha-1.0.0.dist-info/entry_points.txt
pravaha-1.0.0.dist-info/top_level.txt
pravaha-1.0.0.dist-info/RECORD
