Metadata-Version: 2.4
Name: pravaha
Version: 1.0.0
Summary: A lightweight Python task orchestration library for executing dependency-based workflows using a synchronous DAG executor
Author: Aditya Pawar
Requires-Python: >=3.7
Provides-Extra: dev
Requires-Dist: pytest; extra == "dev"
